pyrsistent_mutable/__init__.py
pyrsistent_mutable/ast6.py
pyrsistent_mutable/decorator.py
pyrsistent_mutable/flags.py
pyrsistent_mutable/globals.py
pyrsistent_mutable/rewrite.py
pyrsistent_mutable-0.0.6.dist-info/DESCRIPTION.rst
pyrsistent_mutable-0.0.6.dist-info/METADATA
pyrsistent_mutable-0.0.6.dist-info/RECORD
pyrsistent_mutable-0.0.6.dist-info/WHEEL
pyrsistent_mutable-0.0.6.dist-info/metadata.json
pyrsistent_mutable-0.0.6.dist-info/top_level.txt
pyrsistent_mutable-0.0.6.dist-info/zip-safe
