Metadata-Version: 2.0
Name: pyrsistent-mutable
Version: 0.0.6
Summary: Decorator to create and update immutable values with imperative syntax.
Home-page: https://github.com/scooby/pyrsistent-mutable
Author: Ben Samuel
Author-email: UNKNOWN
License: MIT
Platform: UNKNOWN
Classifier: Development Status :: 3 - Alpha
Classifier: Intended Audience :: Developers
Classifier: Topic :: Software Development :: Build Tools
Classifier: License :: OSI Approved :: MIT License
Classifier: Programming Language :: Python :: 2
Classifier: Programming Language :: Python :: 2.6
Classifier: Programming Language :: Python :: 2.7
Classifier: Programming Language :: Python :: 3
Classifier: Programming Language :: Python :: 3.4
Classifier: Programming Language :: Python :: 3.5
Classifier: Programming Language :: Python :: 3.6
Requires-Python: ~=3.4
Requires-Dist: pyrsistent
Requires-Dist: astunparse
Requires-Dist: six
